__init__.py
cortexpy/__init__.py
cortexpy/__main__.py
cortexpy/cli.py
cortexpy/constants.py
cortexpy/edge_set.py
cortexpy/links.py
cortexpy/logging_config.py
cortexpy/tesserae.py
cortexpy/utils.py
cortexpy/command/__init__.py
cortexpy/command/assemble.py
cortexpy/command/exit_codes.yaml
cortexpy/command/prune.py
cortexpy/command/shared.py
cortexpy/command/subgraph.py
cortexpy/command/traverse.py
cortexpy/command/view.py
cortexpy/graph/__init__.py
cortexpy/graph/contig_retriever.py
cortexpy/graph/cortex.py
cortexpy/graph/interactor.py
cortexpy/graph/interactor_ext.html
cortexpy/graph/parser/__init__.py
cortexpy/graph/parser/constants.py
cortexpy/graph/parser/header.py
cortexpy/graph/parser/kmer.py
cortexpy/graph/parser/kmer_collection.py
cortexpy/graph/parser/kmer_ext.cpp
cortexpy/graph/parser/kmer_ext.cpython-36m-darwin.so
cortexpy/graph/parser/kmer_ext.html
cortexpy/graph/parser/kmer_ext.pyx
cortexpy/graph/parser/random_access.py
cortexpy/graph/parser/random_access_collection.py
cortexpy/graph/parser/streaming.py
cortexpy/graph/serializer/__init__.py
cortexpy/graph/serializer/kmer.py
cortexpy/graph/serializer/serializer.py
cortexpy/graph/serializer/unitig.py
cortexpy/graph/traversal/__init__.py
cortexpy/graph/traversal/branch.py
cortexpy/graph/traversal/engine.py
cortexpy/graph/traversal/utils.py
cortexpy/test/__init__.py
cortexpy/test/constants.py
cortexpy/test/runner.py
cortexpy/test/builder/__init__.py
cortexpy/test/builder/mccortex.py
cortexpy/test/builder/unitig_finder.py
cortexpy/test/builder/unitigs.py
cortexpy/test/builder/graph/__init__.py
cortexpy/test/builder/graph/body.py
cortexpy/test/builder/graph/cortex.py
cortexpy/test/builder/graph/graph.py
cortexpy/test/builder/graph/header.py
cortexpy/test/builder/graph/kmer.py
cortexpy/test/driver/__init__.py
cortexpy/test/driver/command.py
cortexpy/test/driver/graph/__init__.py
cortexpy/test/driver/graph/find_unitigs.py
cortexpy/test/driver/graph/serializer.py
cortexpy/test/driver/graph/traversal.py
cortexpy-0.46.4.dist-info/LICENSE.txt
cortexpy-0.46.4.dist-info/METADATA
cortexpy-0.46.4.dist-info/WHEEL
cortexpy-0.46.4.dist-info/entry_points.txt
cortexpy-0.46.4.dist-info/top_level.txt
cortexpy-0.46.4.dist-info/RECORD
