Metadata-Version: 2.1
Name: cortexpy
Version: 0.46.4
Summary: The python sister project to CortexJDK
Home-page: https://github.com/winni2k/cortexpy
Author: Warren W. Kretzschmar, Kiran V Garimella
Author-email: winni@warrenwk.com, kiran.garimella@gmail.com
License: Apache-2.0
Download-URL: https://github.com/winni2k/cortexpy/archive/0.46.4.tar.gz
Platform: UNKNOWN
Classifier: Development Status :: 3 - Alpha
Classifier: Intended Audience :: Science/Research
Classifier: License :: OSI Approved :: Apache Software License
Classifier: Natural Language :: English
Classifier: Operating System :: OS Independent
Classifier: Programming Language :: Python :: 3.6
Classifier: Programming Language :: Python :: 3.7
Classifier: Programming Language :: Python :: Implementation :: CPython
Requires-Python: >=3.6
Requires-Dist: attrs
Requires-Dist: biopython
Requires-Dist: numpy
Requires-Dist: networkx (==2.1)
Requires-Dist: schema
Requires-Dist: delegation
Requires-Dist: msgpack
Requires-Dist: pyyaml (>=4.2b1)
